odoo10_addon_pos_sequence_ref_number-10.0.1.0.1-nspkg.pth
odoo/addons/pos_sequence_ref_number/README.rst
odoo/addons/pos_sequence_ref_number/__init__.py
odoo/addons/pos_sequence_ref_number/__manifest__.py
odoo/addons/pos_sequence_ref_number/i18n/ca.po
odoo/addons/pos_sequence_ref_number/i18n/de.po
odoo/addons/pos_sequence_ref_number/i18n/es.po
odoo/addons/pos_sequence_ref_number/i18n/fr.po
odoo/addons/pos_sequence_ref_number/i18n/gl.po
odoo/addons/pos_sequence_ref_number/i18n/it.po
odoo/addons/pos_sequence_ref_number/i18n/nl_NL.po
odoo/addons/pos_sequence_ref_number/i18n/pos_sequence_ref_number.pot
odoo/addons/pos_sequence_ref_number/i18n/sl.po
odoo/addons/pos_sequence_ref_number/i18n/zh_CN.po
odoo/addons/pos_sequence_ref_number/models/__init__.py
odoo/addons/pos_sequence_ref_number/models/pos_order.py
odoo/addons/pos_sequence_ref_number/static/description/icon.png
odoo/addons/pos_sequence_ref_number/static/lib/moment.js
odoo/addons/pos_sequence_ref_number/static/src/js/main.js
odoo/addons/pos_sequence_ref_number/static/src/xml/pos.xml
odoo/addons/pos_sequence_ref_number/tests/__init__.py
odoo/addons/pos_sequence_ref_number/tests/test_pos_order.py
odoo/addons/pos_sequence_ref_number/views/pos_template.xml
odoo10_addon_pos_sequence_ref_number-10.0.1.0.1.dist-info/METADATA
odoo10_addon_pos_sequence_ref_number-10.0.1.0.1.dist-info/WHEEL
odoo10_addon_pos_sequence_ref_number-10.0.1.0.1.dist-info/namespace_packages.txt
odoo10_addon_pos_sequence_ref_number-10.0.1.0.1.dist-info/top_level.txt
odoo10_addon_pos_sequence_ref_number-10.0.1.0.1.dist-info/RECORD
