Metadata-Version: 2.1
Name: odoo10-addon-pos-sequence-ref-number
Version: 10.0.1.0.1
Summary: Sequential Order numbers for Point of sale
Home-page: https://github.com/OCA/pos
Author: Eficent Business and IT Consulting Services,Acsone SA/NV,Odoo Community Association (OCA)
Author-email: support@odoo-community.org
License: AGPL-3
Platform: UNKNOWN
Classifier: Programming Language :: Python
Classifier: Framework :: Odoo
Classifier: License :: OSI Approved :: GNU Affero General Public License v3
Requires-Python: ~=2.7
Requires-Dist: odoo (<10.1dev,>=10.0)
